COPYING
MANIFEST.in
README.rst
setup.py
asterisk_mbox/__init__.py
asterisk_mbox/commands.py
asterisk_mbox/utils.py
asterisk_mbox.egg-info/PKG-INFO
asterisk_mbox.egg-info/SOURCES.txt
asterisk_mbox.egg-info/dependency_links.txt
asterisk_mbox.egg-info/top_level.txt