Metadata-Version: 1.0
Name: asterisk-mbox
Version: 0.5.0
Summary: The client side of a client/server to interact with Asterisk voicemail mailboxes
Home-page: https://github.com/PhracturedBlue/asterisk_mbox
Author: PhracturedBlue
Author-email: rc2012@pblue.org
License: UNKNOWN
Keywords: testing,asterisk,mailbox,voicemail
Platform: UNKNOWN
